[
  {
    "image_path": "C:\\Users\\Mohammed Afshan\\MinProject\\dataset\\images\\gatto_15640.jpg",
    "timestamp": "2026-04-28T16:28:41.485401+00:00"
  },
  {
    "image_path": "C:\\Users\\Mohammed Afshan\\MinProject\\dataset\\images\\cane_2414.jpg",
    "timestamp": "2026-04-28T16:36:30.809891+00:00"
  },
  {
    "image_path": "C:\\Users\\Mohammed Afshan\\MinProject\\dataset\\images\\ragno_19789.jpg",
    "timestamp": "2026-04-28T16:51:01.149207+00:00"
  },
  {
    "image_path": "C:\\Users\\Mohammed Afshan\\MinProject\\dataset\\images\\farfalla_9352.jpg",
    "timestamp": "2026-04-28T19:57:01.122662+00:00"
  }
]